LICENSE
README.md
setup.py
eXirt.egg-info/PKG-INFO
eXirt.egg-info/SOURCES.txt
eXirt.egg-info/dependency_links.txt
eXirt.egg-info/requires.txt
eXirt.egg-info/top_level.txt
pyexirt/decodIRT_MLtIRT.py
pyexirt/decodIRT_analysis.py
pyexirt/eXirt.py
pyexirt/eXirt_plots.py